chain_tool/__init__.py
chain_tool/core.py
blockchain_toolkit-0.2.2.dist-info/METADATA
blockchain_toolkit-0.2.2.dist-info/WHEEL
blockchain_toolkit-0.2.2.dist-info/top_level.txt
blockchain_toolkit-0.2.2.dist-info/RECORD
